pilosa_roaring-0.2.1.dist-info/METADATA
pilosa_roaring-0.2.1.dist-info/RECORD
pilosa_roaring-0.2.1.dist-info/WHEEL
pilosa_roaring-0.2.1.dist-info/top_level.txt
roaring/__init__.py
roaring/roaring.py
