Metadata-Version: 2.1
Name: pilosa-roaring
Version: 0.2.1
Summary: Python library for Pilosa Roaring Bitmaps
Home-page: https://github.com/pilosa/python-pilosa-roaring
Author: Pilosa Engineering
Author-email: dev@pilosa.com
License: BSD
Keywords: pilosa,roaring,bitmap
Platform: UNKNOWN
Classifier: Development Status :: 4 - Beta
Classifier: Intended Audience :: Developers
Classifier: License :: OSI Approved :: MIT License
Classifier: Programming Language :: Python :: 2
Classifier: Programming Language :: Python :: 2.7
Classifier: Programming Language :: Python :: 3
Classifier: Programming Language :: Python :: 3.4
Classifier: Programming Language :: Python :: 3.5
Classifier: Programming Language :: Python :: 3.6
Classifier: Operating System :: OS Independent
Classifier: License :: OSI Approved :: BSD License
